apicrusher_lite.py
apicrusher_lite-1.0.0.dist-info/METADATA
apicrusher_lite-1.0.0.dist-info/WHEEL
apicrusher_lite-1.0.0.dist-info/top_level.txt
apicrusher_lite-1.0.0.dist-info/RECORD
