Metadata-Version: 2.4
Name: apicrusher-lite
Version: 1.0.0
Summary: Basic AI model router for cost optimization
Home-page: https://github.com/apicrusher/apicrusher-lite
Author: APICrusher
Author-email: hello@apicrusher.com
Keywords: ai api cost optimization routing openai anthropic llm
Classifier: Development Status :: 4 - Beta
Classifier: Intended Audience :: Developers
Classifier: Topic :: Software Development :: Libraries :: Python Modules
Classifier: Topic :: Scientific/Engineering :: Artificial Intelligence
Classifier: Programming Language :: Python :: 3
Classifier: License :: OSI Approved :: MIT License
Classifier: Operating System :: OS Independent
Requires-Python: >=3.7
Dynamic: author
Dynamic: author-email
Dynamic: classifier
Dynamic: description
Dynamic: description-content-type
Dynamic: home-page
Dynamic: keywords
Dynamic: requires-python
Dynamic: summary
